pyprinty/__init__.py
pyprinty/_animation.py
pyprinty/_colors.py
pyprinty/_colorsgenerator.py
pyprinty/_cursor.py
pyprinty/_effects.py
pyprinty/_font.py
pyprinty/_show.py
pyprinty/_terminal.py
pyprinty-2.1.0.dist-info/licenses/LICENSE
pyprinty-2.1.0.dist-info/METADATA
pyprinty-2.1.0.dist-info/WHEEL
pyprinty-2.1.0.dist-info/top_level.txt
pyprinty-2.1.0.dist-info/RECORD
