Metadata-Version: 2.4
Name: pyprinty
Version: 2.1.0
Summary: Extensions to the print command and strings in general.
Author-email: Yedidya steinmetz <yd.sc.20@gmail.com>
License: MIT
Keywords: print,terminal,text,output,effects,colors,strings,str,fonts,console
Classifier: Programming Language :: Python :: 3
Classifier: License :: OSI Approved :: MIT License
Classifier: Operating System :: OS Independent
Classifier: Intended Audience :: Developers
Classifier: Topic :: Software Development :: Libraries
Requires-Python: >=3.8
License-File: LICENSE
Dynamic: license-file
